{"5859": {"total_avg_value": 0.5546042914851126, "total_avg_sat": 0.11584032316630358, "obj_count": 1, "obj_data": [{"obj_min_x": 258, "obj_max_x": 295, "obj_min_y": 110, "obj_max_y": 144, "obj_avg_value": 0.32979207581283704, "obj_avg_sat": 0.07312572087658592, "obj_std_value": 0.07591381455903923, "obj_std_sat": 0.03658752995426091, "obj_brighten": false}]}, "8970": {"total_avg_value": 0.5608170842411039, "total_avg_sat": 0.12329747639796662, "obj_count": 1, "obj_data": [{"obj_min_x": 138, "obj_max_x": 185, "obj_min_y": 615, "obj_max_y": 647, "obj_avg_value": 0.4322108345534408, "obj_avg_sat": 0.08708982861080011, "obj_std_value": 0.04771237545211993, "obj_std_sat": 0.015138779870854784, "obj_brighten": true}]}, "8971": {"total_avg_value": 0.5611713076434277, "total_avg_sat": 0.1249540214233842, "obj_count": 1, "obj_data": [{"obj_min_x": 167, "obj_max_x": 197, "obj_min_y": 603, "obj_max_y": 646, "obj_avg_value": 0.4086940436551979, "obj_avg_sat": 0.08013318534961153, "obj_std_value": 0.03001325171599478, "obj_std_sat": 0.013680692900454112, "obj_brighten": true}]}, "8976": {"total_avg_value": 0.5576713984204795, "total_avg_sat": 0.1267998933369644, "obj_count": 1, "obj_data": [{"obj_min_x": 167, "obj_max_x": 192, "obj_min_y": 593, "obj_max_y": 647, "obj_avg_value": 0.4376100516310025, "obj_avg_sat": 0.04459963589697675, "obj_std_value": 0.03508120187018932, "obj_std_sat": 0.03569593749257533, "obj_brighten": false}]}, "8977": {"total_avg_value": 0.5568536446986202, "total_avg_sat": 0.1279028685548293, "obj_count": 1, "obj_data": [{"obj_min_x": 139, "obj_max_x": 180, "obj_min_y": 604, "obj_max_y": 649, "obj_avg_value": 0.42685150493318347, "obj_avg_sat": 0.062089421755963534, "obj_std_value": 0.031163961270786862, "obj_std_sat": 0.04113792800490901, "obj_brighten": true}]}, "8982": {"total_avg_value": 0.553049575617284, "total_avg_sat": 0.12786520742556284, "obj_count": 1, "obj_data": [{"obj_min_x": 146, "obj_max_x": 178, "obj_min_y": 478, "obj_max_y": 509, "obj_avg_value": 0.44441627225602887, "obj_avg_sat": 0.05681203515889114, "obj_std_value": 0.03825189450273978, "obj_std_sat": 0.014317911049849611, "obj_brighten": false}]}, "8983": {"total_avg_value": 0.5522618917937545, "total_avg_sat": 0.12763543936092958, "obj_count": 1, "obj_data": [{"obj_min_x": 147, "obj_max_x": 178, "obj_min_y": 476, "obj_max_y": 507, "obj_avg_value": 0.46975176519792355, "obj_avg_sat": 0.08114251974315448, "obj_std_value": 0.043392526324846484, "obj_std_sat": 0.015305279291447657, "obj_brighten": true}]}, "8984": {"total_avg_value": 0.5515045615468409, "total_avg_sat": 0.12658879130355843, "obj_count": 2, "obj_data": [{"obj_min_x": 147, "obj_max_x": 176, "obj_min_y": 475, "obj_max_y": 507, "obj_avg_value": 0.474955680902498, "obj_avg_sat": 0.08969648133225894, "obj_std_value": 0.05704345086151621, "obj_std_sat": 0.024519053663612744, "obj_brighten": true}, {"obj_min_x": 149, "obj_max_x": 175, "obj_min_y": 436, "obj_max_y": 472, "obj_avg_value": 0.4717460317460318, "obj_avg_sat": 0.08031123560535325, "obj_std_value": 0.02749322511499174, "obj_std_sat": 0.015702786008058474, "obj_brighten": false}]}, "8986": {"total_avg_value": 0.5501889978213508, "total_avg_sat": 0.12653250953159043, "obj_count": 1, "obj_data": [{"obj_min_x": 153, "obj_max_x": 183, "obj_min_y": 392, "obj_max_y": 432, "obj_avg_value": 0.48192568856336315, "obj_avg_sat": 0.08054729025202818, "obj_std_value": 0.033388369451915166, "obj_std_sat": 0.012821443025814293, "obj_brighten": false}]}, "8989": {"total_avg_value": 0.5500285153413217, "total_avg_sat": 0.12515475217864924, "obj_count": 1, "obj_data": [{"obj_min_x": 215, "obj_max_x": 242, "obj_min_y": 191, "obj_max_y": 228, "obj_avg_value": 0.3822140754318725, "obj_avg_sat": 0.08653002277398211, "obj_std_value": 0.060750818093839795, "obj_std_sat": 0.03762391981350115, "obj_brighten": false}]}, "8990": {"total_avg_value": 0.5502514297385619, "total_avg_sat": 0.12467914851125636, "obj_count": 2, "obj_data": [{"obj_min_x": 172, "obj_max_x": 210, "obj_min_y": 216, "obj_max_y": 252, "obj_avg_value": 0.40965686274509805, "obj_avg_sat": 0.07147950089126559, "obj_std_value": 0.043690097523912855, "obj_std_sat": 0.02560598460174617, "obj_brighten": true}, {"obj_min_x": 207, "obj_max_x": 242, "obj_min_y": 171, "obj_max_y": 300, "obj_avg_value": 0.4147512651224092, "obj_avg_sat": 0.04851853233366904, "obj_std_value": 0.05242995154284657, "obj_std_sat": 0.037568253750579435, "obj_brighten": false}]}, "8991": {"total_avg_value": 0.5504239515250544, "total_avg_sat": 0.12304086102033406, "obj_count": 3, "obj_data": [{"obj_min_x": 169, "obj_max_x": 210, "obj_min_y": 216, "obj_max_y": 253, "obj_avg_value": 0.4130869082661776, "obj_avg_sat": 0.0609435570782866, "obj_std_value": 0.03210991987362778, "obj_std_sat": 0.02296357823436915, "obj_brighten": false}, {"obj_min_x": 174, "obj_max_x": 216, "obj_min_y": 165, "obj_max_y": 203, "obj_avg_value": 0.44695138329304324, "obj_avg_sat": 0.047112543647596025, "obj_std_value": 0.07751485067672885, "obj_std_sat": 0.032571070723565056, "obj_brighten": false}, {"obj_min_x": 210, "obj_max_x": 241, "obj_min_y": 173, "obj_max_y": 275, "obj_avg_value": 0.42248025746813545, "obj_avg_sat": 0.03109750046077722, "obj_std_value": 0.04296652773051606, "obj_std_sat": 0.016518478827412926, "obj_brighten": true}]}, "8992": {"total_avg_value": 0.5510214347312998, "total_avg_sat": 0.12213062817719678, "obj_count": 2, "obj_data": [{"obj_min_x": 170, "obj_max_x": 216, "obj_min_y": 165, "obj_max_y": 253, "obj_avg_value": 0.432061116162676, "obj_avg_sat": 0.049600149215453124, "obj_std_value": 0.04500593342475638, "obj_std_sat": 0.021167081776726555, "obj_brighten": false}, {"obj_min_x": 210, "obj_max_x": 241, "obj_min_y": 173, "obj_max_y": 269, "obj_avg_value": 0.410640709173614, "obj_avg_sat": 0.03807926971263565, "obj_std_value": 0.04360599138157748, "obj_std_sat": 0.019968715322187122, "obj_brighten": false}]}, "8993": {"total_avg_value": 0.5524033451343499, "total_avg_sat": 0.11968476534132173, "obj_count": 2, "obj_data": [{"obj_min_x": 170, "obj_max_x": 216, "obj_min_y": 162, "obj_max_y": 253, "obj_avg_value": 0.4268524752946617, "obj_avg_sat": 0.05631252848000109, "obj_std_value": 0.05480378266606958, "obj_std_sat": 0.029118783285519454, "obj_brighten": false}, {"obj_min_x": 212, "obj_max_x": 233, "obj_min_y": 172, "obj_max_y": 251, "obj_avg_value": 0.4085080566880218, "obj_avg_sat": 0.0531935546495826, "obj_std_value": 0.049431346142907694, "obj_std_sat": 0.025527000841839894, "obj_brighten": false}]}, "8994": {"total_avg_value": 0.5529630991285401, "total_avg_sat": 0.11909517973856211, "obj_count": 3, "obj_data": [{"obj_min_x": 171, "obj_max_x": 212, "obj_min_y": 207, "obj_max_y": 253, "obj_avg_value": 0.38613221776373824, "obj_avg_sat": 0.08778849711147159, "obj_std_value": 0.036596973327044334, "obj_std_sat": 0.035539683526761505, "obj_brighten": false}, {"obj_min_x": 173, "obj_max_x": 216, "obj_min_y": 161, "obj_max_y": 223, "obj_avg_value": 0.45913643416817346, "obj_avg_sat": 0.05543287295297451, "obj_std_value": 0.060799040103145324, "obj_std_sat": 0.032296219366052245, "obj_brighten": false}, {"obj_min_x": 215, "obj_max_x": 242, "obj_min_y": 172, "obj_max_y": 251, "obj_avg_value": 0.40277740041359117, "obj_avg_sat": 0.09002400036226961, "obj_std_value": 0.04817988017960737, "obj_std_sat": 0.03550272841876594, "obj_brighten": false}]}, "8995": {"total_avg_value": 0.5554243146332606, "total_avg_sat": 0.11862325254175744, "obj_count": 3, "obj_data": [{"obj_min_x": 174, "obj_max_x": 216, "obj_min_y": 161, "obj_max_y": 223, "obj_avg_value": 0.43163855199568074, "obj_avg_sat": 0.09119424801485403, "obj_std_value": 0.05986214417382246, "obj_std_sat": 0.037063436998385976, "obj_brighten": true}, {"obj_min_x": 179, "obj_max_x": 212, "obj_min_y": 206, "obj_max_y": 253, "obj_avg_value": 0.3718991414599959, "obj_avg_sat": 0.09202465714149186, "obj_std_value": 0.03829638676130802, "obj_std_sat": 0.02984911363873424, "obj_brighten": false}, {"obj_min_x": 212, "obj_max_x": 242, "obj_min_y": 172, "obj_max_y": 256, "obj_avg_value": 0.39660033167495856, "obj_avg_sat": 0.1093868890839918, "obj_std_value": 0.05201238916868681, "obj_std_sat": 0.03872520498648506, "obj_brighten": false}]}, "8996": {"total_avg_value": 0.5574804602396515, "total_avg_sat": 0.1186660993100944, "obj_count": 2, "obj_data": [{"obj_min_x": 174, "obj_max_x": 216, "obj_min_y": 161, "obj_max_y": 241, "obj_avg_value": 0.414726086705536, "obj_avg_sat": 0.1087167349766207, "obj_std_value": 0.0570763521648333, "obj_std_sat": 0.0478806956364482, "obj_brighten": false}, {"obj_min_x": 215, "obj_max_x": 242, "obj_min_y": 172, "obj_max_y": 235, "obj_avg_value": 0.3892379679144385, "obj_avg_sat": 0.09258658008658008, "obj_std_value": 0.06274713321789231, "obj_std_sat": 0.04353292262751596, "obj_brighten": false}]}, "8997": {"total_avg_value": 0.5605213893427742, "total_avg_sat": 0.11719303740014528, "obj_count": 2, "obj_data": [{"obj_min_x": 191, "obj_max_x": 216, "obj_min_y": 165, "obj_max_y": 203, "obj_avg_value": 0.3985531534551142, "obj_avg_sat": 0.06927545947153789, "obj_std_value": 0.04696083195917593, "obj_std_sat": 0.02046735345335083, "obj_brighten": false}, {"obj_min_x": 218, "obj_max_x": 241, "obj_min_y": 172, "obj_max_y": 211, "obj_avg_value": 0.40151841224294593, "obj_avg_sat": 0.07950143472022955, "obj_std_value": 0.11499253489479709, "obj_std_sat": 0.044404497346273795, "obj_brighten": false}]}, "9002": {"total_avg_value": 0.5755823120915031, "total_avg_sat": 0.11931032135076251, "obj_count": 1, "obj_data": [{"obj_min_x": 196, "obj_max_x": 232, "obj_min_y": 28, "obj_max_y": 61, "obj_avg_value": 0.4388951220815302, "obj_avg_sat": 0.06368007693540631, "obj_std_value": 0.057762345811362296, "obj_std_sat": 0.037222768855078234, "obj_brighten": false}]}, "9395": {"total_avg_value": 0.5573170955882351, "total_avg_sat": 0.12388356708424103, "obj_count": 1, "obj_data": [{"obj_min_x": 220, "obj_max_x": 242, "obj_min_y": 214, "obj_max_y": 249, "obj_avg_value": 0.9283344106873519, "obj_avg_sat": 0.013568504324806845, "obj_std_value": 0.07140147156542308, "obj_std_sat": 0.01182736333775899, "obj_brighten": true}]}, "9396": {"total_avg_value": 0.5579853395061729, "total_avg_sat": 0.12420149101307192, "obj_count": 1, "obj_data": [{"obj_min_x": 220, "obj_max_x": 242, "obj_min_y": 214, "obj_max_y": 250, "obj_avg_value": 0.927688651218063, "obj_avg_sat": 0.013469994058229353, "obj_std_value": 0.07259711205805264, "obj_std_sat": 0.01245377410033036, "obj_brighten": true}]}, "9397": {"total_avg_value": 0.5588585353122729, "total_avg_sat": 0.12423361474219319, "obj_count": 1, "obj_data": [{"obj_min_x": 220, "obj_max_x": 240, "obj_min_y": 214, "obj_max_y": 251, "obj_avg_value": 0.9293577981651375, "obj_avg_sat": 0.01254422258199916, "obj_std_value": 0.06911354860964275, "obj_std_sat": 0.01071023308014174, "obj_brighten": true}]}, "9398": {"total_avg_value": 0.5588992034313726, "total_avg_sat": 0.12458859840232393, "obj_count": 1, "obj_data": [{"obj_min_x": 220, "obj_max_x": 241, "obj_min_y": 215, "obj_max_y": 252, "obj_avg_value": 0.925513643424485, "obj_avg_sat": 0.012685014214953542, "obj_std_value": 0.07174461364045187, "obj_std_sat": 0.011240257608978498, "obj_brighten": true}]}, "9399": {"total_avg_value": 0.5610264955519247, "total_avg_sat": 0.12741404547930285, "obj_count": 1, "obj_data": [{"obj_min_x": 220, "obj_max_x": 240, "obj_min_y": 216, "obj_max_y": 253, "obj_avg_value": 0.9257684591988611, "obj_avg_sat": 0.01452145214521452, "obj_std_value": 0.0715264321040808, "obj_std_sat": 0.012078196318884201, "obj_brighten": true}]}, "20806": {"total_avg_value": 0.5612530750726217, "total_avg_sat": 0.10553736610384895, "obj_count": 1, "obj_data": [{"obj_min_x": 203, "obj_max_x": 254, "obj_min_y": 105, "obj_max_y": 127, "obj_avg_value": 0.9206564996368919, "obj_avg_sat": 0.13634858387799564, "obj_std_value": 0.06335298902230728, "obj_std_sat": 0.04750453334014125, "obj_brighten": true}]}, "20807": {"total_avg_value": 0.5617866285403049, "total_avg_sat": 0.10634356844589686, "obj_count": 1, "obj_data": [{"obj_min_x": 191, "obj_max_x": 254, "obj_min_y": 105, "obj_max_y": 128, "obj_avg_value": 0.9161033155918068, "obj_avg_sat": 0.12731964701274165, "obj_std_value": 0.0645342266535552, "obj_std_sat": 0.04480074183775622, "obj_brighten": true}]}, "20808": {"total_avg_value": 0.5620587440994915, "total_avg_sat": 0.10691178740014523, "obj_count": 1, "obj_data": [{"obj_min_x": 190, "obj_max_x": 250, "obj_min_y": 104, "obj_max_y": 134, "obj_avg_value": 0.8945072629483761, "obj_avg_sat": 0.11513996527336637, "obj_std_value": 0.0736000715965277, "obj_std_sat": 0.040557145393939203, "obj_brighten": true}]}, "20809": {"total_avg_value": 0.5615595043572984, "total_avg_sat": 0.10648432961147421, "obj_count": 1, "obj_data": [{"obj_min_x": 184, "obj_max_x": 249, "obj_min_y": 100, "obj_max_y": 142, "obj_avg_value": 0.8952917285277906, "obj_avg_sat": 0.1087424700080206, "obj_std_value": 0.07234503593917746, "obj_std_sat": 0.04526741858545117, "obj_brighten": true}]}, "20810": {"total_avg_value": 0.561822008896151, "total_avg_sat": 0.1067854484386347, "obj_count": 1, "obj_data": [{"obj_min_x": 184, "obj_max_x": 253, "obj_min_y": 102, "obj_max_y": 149, "obj_avg_value": 0.8948626827519559, "obj_avg_sat": 0.11090121263131643, "obj_std_value": 0.07278950386862723, "obj_std_sat": 0.046528426526449305, "obj_brighten": true}]}, "20811": {"total_avg_value": 0.5630608546659405, "total_avg_sat": 0.10467814996368917, "obj_count": 1, "obj_data": [{"obj_min_x": 185, "obj_max_x": 253, "obj_min_y": 104, "obj_max_y": 150, "obj_avg_value": 0.914642391860024, "obj_avg_sat": 0.11654875575124919, "obj_std_value": 0.06960131036772703, "obj_std_sat": 0.047765346834382265, "obj_brighten": true}]}, "20812": {"total_avg_value": 0.5627551515976759, "total_avg_sat": 0.10496968046477853, "obj_count": 1, "obj_data": [{"obj_min_x": 185, "obj_max_x": 251, "obj_min_y": 104, "obj_max_y": 150, "obj_avg_value": 0.9176852177996947, "obj_avg_sat": 0.10886168838793002, "obj_std_value": 0.06783460511642794, "obj_std_sat": 0.04848788444361633, "obj_brighten": true}]}, "20813": {"total_avg_value": 0.5624319172113288, "total_avg_sat": 0.10392834286492376, "obj_count": 1, "obj_data": [{"obj_min_x": 186, "obj_max_x": 251, "obj_min_y": 102, "obj_max_y": 150, "obj_avg_value": 0.9188235294117647, "obj_avg_sat": 0.10643364592213697, "obj_std_value": 0.06780350591086022, "obj_std_sat": 0.053839507428296574, "obj_brighten": true}]}, "20814": {"total_avg_value": 0.5622799791212781, "total_avg_sat": 0.1047472199527959, "obj_count": 1, "obj_data": [{"obj_min_x": 186, "obj_max_x": 250, "obj_min_y": 101, "obj_max_y": 157, "obj_avg_value": 0.9168970320368586, "obj_avg_sat": 0.10764491588985321, "obj_std_value": 0.06798790087100429, "obj_std_sat": 0.05338400889876271, "obj_brighten": true}]}, "20815": {"total_avg_value": 0.5621814292846767, "total_avg_sat": 0.10546099990922296, "obj_count": 1, "obj_data": [{"obj_min_x": 183, "obj_max_x": 250, "obj_min_y": 101, "obj_max_y": 160, "obj_avg_value": 0.9083179636097267, "obj_avg_sat": 0.11442137895852135, "obj_std_value": 0.06756758712399903, "obj_std_sat": 0.061474766045379096, "obj_brighten": false}]}, "20816": {"total_avg_value": 0.5619209899237471, "total_avg_sat": 0.10511321033042846, "obj_count": 1, "obj_data": [{"obj_min_x": 187, "obj_max_x": 250, "obj_min_y": 102, "obj_max_y": 150, "obj_avg_value": 0.9024418689408851, "obj_avg_sat": 0.11538450324367665, "obj_std_value": 0.07142002958896321, "obj_std_sat": 0.05744152838414379, "obj_brighten": true}]}, "20817": {"total_avg_value": 0.5621505310457515, "total_avg_sat": 0.10589889705882351, "obj_count": 1, "obj_data": [{"obj_min_x": 185, "obj_max_x": 250, "obj_min_y": 99, "obj_max_y": 150, "obj_avg_value": 0.8911220818341562, "obj_avg_sat": 0.11283016762892922, "obj_std_value": 0.06431558302741469, "obj_std_sat": 0.05113995242695142, "obj_brighten": true}]}, "20818": {"total_avg_value": 0.5620586306281773, "total_avg_sat": 0.10602086737472767, "obj_count": 1, "obj_data": [{"obj_min_x": 185, "obj_max_x": 254, "obj_min_y": 102, "obj_max_y": 150, "obj_avg_value": 0.8895244285559529, "obj_avg_sat": 0.12128155129455098, "obj_std_value": 0.06738601409623718, "obj_std_sat": 0.05394438614058467, "obj_brighten": false}]}, "20819": {"total_avg_value": 0.5620918777233115, "total_avg_sat": 0.1067402982026144, "obj_count": 1, "obj_data": [{"obj_min_x": 185, "obj_max_x": 256, "obj_min_y": 96, "obj_max_y": 150, "obj_avg_value": 0.8862272320095551, "obj_avg_sat": 0.11939136060515579, "obj_std_value": 0.06957533133824621, "obj_std_sat": 0.05613590763205211, "obj_brighten": true}]}, "20820": {"total_avg_value": 0.561209831154684, "total_avg_sat": 0.1051170797022513, "obj_count": 1, "obj_data": [{"obj_min_x": 186, "obj_max_x": 253, "obj_min_y": 103, "obj_max_y": 150, "obj_avg_value": 0.8861676326715173, "obj_avg_sat": 0.12336635562680698, "obj_std_value": 0.06866848165604102, "obj_std_sat": 0.058282109917689826, "obj_brighten": true}]}, "20821": {"total_avg_value": 0.5612434527051562, "total_avg_sat": 0.10558144970951343, "obj_count": 1, "obj_data": [{"obj_min_x": 187, "obj_max_x": 253, "obj_min_y": 105, "obj_max_y": 150, "obj_avg_value": 0.8870566048201458, "obj_avg_sat": 0.1251934437141193, "obj_std_value": 0.06807325065762394, "obj_std_sat": 0.05819027577553204, "obj_brighten": true}]}, "20822": {"total_avg_value": 0.5612699709513436, "total_avg_sat": 0.10648267293028324, "obj_count": 1, "obj_data": [{"obj_min_x": 187, "obj_max_x": 253, "obj_min_y": 105, "obj_max_y": 150, "obj_avg_value": 0.8877421391091649, "obj_avg_sat": 0.12643442353467207, "obj_std_value": 0.06615867071190931, "obj_std_sat": 0.055877403701897234, "obj_brighten": true}]}, "20823": {"total_avg_value": 0.560798384168482, "total_avg_sat": 0.10657999727668849, "obj_count": 1, "obj_data": [{"obj_min_x": 187, "obj_max_x": 252, "obj_min_y": 105, "obj_max_y": 150, "obj_avg_value": 0.8937897297369941, "obj_avg_sat": 0.12870754881801932, "obj_std_value": 0.0638370920284324, "obj_std_sat": 0.056899825419058754, "obj_brighten": true}]}, "20824": {"total_avg_value": 0.5612526325344953, "total_avg_sat": 0.10766400009077706, "obj_count": 1, "obj_data": [{"obj_min_x": 185, "obj_max_x": 252, "obj_min_y": 105, "obj_max_y": 150, "obj_avg_value": 0.8944869914724893, "obj_avg_sat": 0.13083754277334203, "obj_std_value": 0.06220960517696715, "obj_std_sat": 0.05632804589858939, "obj_brighten": true}]}, "20825": {"total_avg_value": 0.5612781522331153, "total_avg_sat": 0.10811429965504721, "obj_count": 1, "obj_data": [{"obj_min_x": 185, "obj_max_x": 251, "obj_min_y": 105, "obj_max_y": 150, "obj_avg_value": 0.8866270410603266, "obj_avg_sat": 0.13249982919997266, "obj_std_value": 0.06408735479001633, "obj_std_sat": 0.05670812451052009, "obj_brighten": true}]}, "20826": {"total_avg_value": 0.5609271968046479, "total_avg_sat": 0.10860346314451703, "obj_count": 1, "obj_data": [{"obj_min_x": 185, "obj_max_x": 251, "obj_min_y": 106, "obj_max_y": 149, "obj_avg_value": 0.8762601911107215, "obj_avg_sat": 0.12655387043043745, "obj_std_value": 0.06534140320684609, "obj_std_sat": 0.05286533694804222, "obj_brighten": false}]}, "20827": {"total_avg_value": 0.5601660085330431, "total_avg_sat": 0.10698985566448799, "obj_count": 1, "obj_data": [{"obj_min_x": 185, "obj_max_x": 230, "obj_min_y": 106, "obj_max_y": 149, "obj_avg_value": 0.8644499566895033, "obj_avg_sat": 0.1251437121033152, "obj_std_value": 0.0704871880492731, "obj_std_sat": 0.051823610571338316, "obj_brighten": false}]}, "20828": {"total_avg_value": 0.5602308006535948, "total_avg_sat": 0.10753858024691358, "obj_count": 1, "obj_data": [{"obj_min_x": 185, "obj_max_x": 230, "obj_min_y": 107, "obj_max_y": 150, "obj_avg_value": 0.8584222718623316, "obj_avg_sat": 0.11388268387523787, "obj_std_value": 0.07222721880493811, "obj_std_sat": 0.04746017536452783, "obj_brighten": false}]}, "20829": {"total_avg_value": 0.5600902210421207, "total_avg_sat": 0.10808755446623092, "obj_count": 1, "obj_data": [{"obj_min_x": 187, "obj_max_x": 254, "obj_min_y": 106, "obj_max_y": 150, "obj_avg_value": 0.8556644880174293, "obj_avg_sat": 0.1201204664872485, "obj_std_value": 0.0673347914561372, "obj_std_sat": 0.04764061697074829, "obj_brighten": false}]}, "20830": {"total_avg_value": 0.559675142973856, "total_avg_sat": 0.10738874137618008, "obj_count": 1, "obj_data": [{"obj_min_x": 192, "obj_max_x": 246, "obj_min_y": 107, "obj_max_y": 150, "obj_avg_value": 0.8462602951628413, "obj_avg_sat": 0.11494209624148166, "obj_std_value": 0.06500489081102982, "obj_std_sat": 0.045800791346373576, "obj_brighten": false}]}, "20831": {"total_avg_value": 0.5597548338779957, "total_avg_sat": 0.10787413761801018, "obj_count": 1, "obj_data": [{"obj_min_x": 198, "obj_max_x": 228, "obj_min_y": 108, "obj_max_y": 149, "obj_avg_value": 0.8491790974763112, "obj_avg_sat": 0.109122181568002, "obj_std_value": 0.06537430727432136, "obj_std_sat": 0.036519925374658965, "obj_brighten": false}]}}